grade_analysis/.history.json
grade_analysis/Athletic_Logo_Block_F.png
grade_analysis/dictionary.py
grade_analysis/fake-example-short-data.csv
grade_analysis/gradeAnalysisFunc.py
grade_analysis/gradeAnalysisGUI.py
grade_analysis/gradeAnalysisWidgets.py
grade_analysis-1.0.3.dist-info/METADATA
grade_analysis-1.0.3.dist-info/WHEEL
grade_analysis-1.0.3.dist-info/entry_points.txt
grade_analysis-1.0.3.dist-info/RECORD
