Metadata-Version: 2.3
Name: grade-analysis
Version: 1.0.3
Summary: Tool for analyzing grading analysis data
License: GPL-3.0-or-later
Author: Mario Marku
Author-email: mariom@fordham.edu
Requires-Python: >=3.9,<4.0
Classifier: License :: OSI Approved :: GNU General Public License v3 or later (GPLv3+)
Classifier: Programming Language :: Python :: 3
Classifier: Programming Language :: Python :: 3.9
Classifier: Programming Language :: Python :: 3.10
Classifier: Programming Language :: Python :: 3.11
Classifier: Programming Language :: Python :: 3.12
Classifier: Programming Language :: Python :: 3.13
Requires-Dist: Requests
Requires-Dist: matplotlib
Requires-Dist: mplcursors
Requires-Dist: numpy
Requires-Dist: pandas
Requires-Dist: prompt_toolkit
Requires-Dist: scikit_learn
Requires-Dist: seaborn
Requires-Dist: tabulate
Requires-Dist: ttkwidgets
Requires-Dist: webcolors
Project-URL: Homepage, https://www.cis.fordham.edu/edmlab/software/grade-analysis-tool
Project-URL: Repository, https://github.com/Fordham-EDM-Lab/Grading-Analysis-Tool/issues
